lineworks/__init__.py
lineworks/action.py
lineworks/quick_reply_items.py
lineworks/server_api.py
lineworks/talkbot_api.py
lineworks-0.1.0.dist-info/METADATA
lineworks-0.1.0.dist-info/WHEEL
lineworks-0.1.0.dist-info/top_level.txt
lineworks-0.1.0.dist-info/RECORD
