Metadata-Version: 2.1
Name: lineworks
Version: 0.1.0
Summary: It is a package that implements the server API and the Talk Bot API among the LINE WORKS APIs.
Home-page: https://github.com/0yan/lineworks
Author: Rei Suzuki
Author-email: re1yanwork@gmail.com
License: MIT License
Keywords: LINE WORKS
Platform: UNKNOWN
Classifier: Programming Language :: Python :: 3.7
Requires-Dist: cryptography (>=2.8)
Requires-Dist: PyJWT (>=1.7.1)
Requires-Dist: requests (>=2.14.2)
